pykm3_codec/__init__.py
pykm3_codec/byte_converter.py
pykm3_codec/character_maps.py
pykm3_codec/pk_codecs.py
pykm3_codec/registry.py
pykm3_codec-0.5.1.dist-info/LICENSE
pykm3_codec-0.5.1.dist-info/METADATA
pykm3_codec-0.5.1.dist-info/WHEEL
pykm3_codec-0.5.1.dist-info/top_level.txt
pykm3_codec-0.5.1.dist-info/RECORD
