Metadata-Version: 2.1
Name: pykm3-codec
Version: 0.5.1
Summary: Pokémon Generation III Text Codec
Author-email: Juan Franco <pykm3.codec@juanfg.es>
License: AGPL-3.0-or-later
Project-URL: Homepage, https://github.com/FrogCosmonaut/pykm3-codec
Project-URL: Bug Tracker, https://github.com/FrogCosmonaut/pykm3-codec/issues
Classifier: Programming Language :: Python :: 3
Classifier: License :: OSI Approved :: GNU Affero General Public License v3 or later (AGPLv3+)
Classifier: Operating System :: OS Independent
Requires-Python: >=3.8
License-File: LICENSE
